daily/__init__.py
daily/config.py
daily/load.py
daily/main.py
daily/parser.py
daily/parsergroups.py
daily/cli/__init__.py
daily/cli/add/__init__.py
daily/cli/add/main.py
daily/cli/add/parser.py
daily/cli/show/__init__.py
daily/cli/show/main.py
daily/cli/show/parser.py
daily/cli/todo/__init__.py
daily/cli/todo/main.py
daily/cli/todo/parser.py
daily_cli-2.1.2.data/data/etc/bash_completion.d/daily_completion.sh
daily_cli-2.1.2.data/data/usr/share/man/man1/daily-add.1.gz
daily_cli-2.1.2.data/data/usr/share/man/man1/daily-show.1.gz
daily_cli-2.1.2.data/data/usr/share/man/man1/daily-todo.1.gz
daily_cli-2.1.2.data/data/usr/share/man/man1/daily.1.gz
daily_cli-2.1.2.dist-info/LICENSE
daily_cli-2.1.2.dist-info/METADATA
daily_cli-2.1.2.dist-info/WHEEL
daily_cli-2.1.2.dist-info/entry_points.txt
daily_cli-2.1.2.dist-info/top_level.txt
daily_cli-2.1.2.dist-info/RECORD
