Metadata-Version: 2.1
Name: daily-cli
Version: 2.1.2
Summary: Command-line notebook for daily entries.
Home-page: https://github.com/OneRedDime/daily
Author: OneRedDime
Author-email: onereddime@protonmail.com
License: GPLv2
Requires-Python: >=3, <4
License-File: LICENSE
Requires-Dist: argcomplete
Requires-Dist: libzet
